<?xml version="1.0" encoding="utf-8"?>
<!DOCTYPE hibernate-mapping PUBLIC "-//Hibernate/Hibernate Mapping DTD 3.0//EN"
"http://hibernate.sourceforge.net/hibernate-mapping-3.0.dtd">
<!-- 
    Mapping file autogenerated by MyEclipse Persistence Tools
-->
<hibernate-mapping>
    <class name="com.selfsoft.baseinformation.model.TbCustomer" table="TB_CUSTOMER"
    dynamic-insert="true"
    dynamic-update="true"
    lazy="false"
    >
        <id name="id" type="java.lang.Long">
            <column name="ID" />
            <generator class="native" />
        </id>
        <property name="customerCode" type="java.lang.String">
            <column name="CUSTOMER_CODE"/>
        </property>
        <property name="customerName" type="java.lang.String">
            <column name="CUSTOMER_NAME"/>
        </property>
        <property name="pinyinCode" type="java.lang.String">
            <column name="PINYIN_CODE"/>
        </property>
        <property name="address" type="java.lang.String">
            <column name="ADDRESS"/>
        </property>
        <property name="phone" type="java.lang.String">
            <column name="PHONE"/>
        </property>
        <property name="telephone" type="java.lang.String">
            <column name="TELEPHONE"/>
        </property>
        <property name="zipCode" type="java.lang.String">
            <column name="ZIP_CODE"/>
        </property>
        <property name="companyAccountCode" type="java.lang.String">
            <column name="COMPANY_ACCOUNT_CODE"/>
        </property>
        <property name="companyTaxCode" type="java.lang.String">
            <column name="COMPANY_TAX_CODE"/>
        </property>
        <property name="lawPresent" type="java.lang.String">
            <column name="LAW_PRESENT"/>
        </property>
        <property name="contractPerson" type="java.lang.String">
            <column name="CONTRACT_PERSON"/>
        </property>
        <property name="customerProperty" type="java.lang.Long">
            <column name="CUSTOMER_PROPERTY" />
        </property>
        <many-to-one name="tmCustomerType" class="com.selfsoft.baseparameter.model.TmCustomerType" fetch="select">
            <column name="CUSTOMER_TYPE_ID" />
        </many-to-one>
        <many-to-one name="tmSoleType" class="com.selfsoft.baseparameter.model.TmSoleType" fetch="select">
            <column name="SOLE_TYPE_ID" />
        </many-to-one>
        <set 
        	name="tbCarInfos" 
        	table="TB_CAR_INFO"
        	inverse="true"
        	cascade="none"
        	>
            <key>
                <column name="CUSTOMER_ID" />
            </key>
            <one-to-many class="com.selfsoft.baseinformation.model.TbCarInfo" />
        </set>
        <set 
        	name="tbFixEntrusts" 
        	table="TB_FIX_ENTRUST"
        	inverse="true"
        	cascade="none"
        	>
            <key>
                <column name="CUSTOMER_ID" />
            </key>
            <one-to-many class="com.selfsoft.business.model.TbFixEntrust" />
       </set>
       <set 
        	name="tbReceiveFrees" 
        	table="TB_RECEIVE_FREE"
        	inverse="true"
        	cascade="none"
        	>
            <key>
                <column name="CUSTOMER_ID" />
            </key>
            <one-to-many class="com.selfsoft.business.model.TbReceiveFree" />
       </set>
    </class>
</hibernate-mapping>
